dspac_invest_api/__init__.py
dspac_invest_api/dspac_api.py
dspac_invest_api-0.1.3.dist-info/LICENSE
dspac_invest_api-0.1.3.dist-info/METADATA
dspac_invest_api-0.1.3.dist-info/WHEEL
dspac_invest_api-0.1.3.dist-info/top_level.txt
dspac_invest_api-0.1.3.dist-info/RECORD
