Metadata-Version: 2.1
Name: dspac_invest_api
Version: 0.1.3
Summary: Unofficial dSPAC Invest API written in Python Requests
Home-page: https://github.com/ImNotOssy/dSPAC_investing_API
Author: Oswaldo Romero
License-File: LICENSE
Requires-Dist: pillow
Requires-Dist: python-dotenv
Requires-Dist: requests
